sphinxext_autox/__init__.py
sphinxext_autox/typing.py
sphinxext_autox/sphinx/ext/autodoc/__init__.py
sphinxext_autox/sphinx/ext/autodoc/deprecated.py
sphinxext_autox/sphinx/ext/autodoc/directive.py
sphinxext_autox/sphinx/ext/autodoc/importer.py
sphinxext_autox/sphinx/ext/autodoc/mock.py
sphinxext_autox/sphinx/ext/autodoc/preserve_defaults.py
sphinxext_autox/sphinx/ext/autodoc/type_comment.py
sphinxext_autox/sphinx/ext/autodoc/typehints.py
sphinxext_autox/sphinx/ext/autosummary/__init__.py
sphinxext_autox/sphinx/ext/autosummary/generate.py
sphinxext_autox/sphinx/ext/autosummary/templates/autosummary/base.rst
sphinxext_autox/sphinx/ext/autosummary/templates/autosummary/class.rst
sphinxext_autox/sphinx/ext/autosummary/templates/autosummary/module.rst
sphinxext_autox-0.0.2.dist-info/METADATA
sphinxext_autox-0.0.2.dist-info/WHEEL
sphinxext_autox-0.0.2.dist-info/top_level.txt
sphinxext_autox-0.0.2.dist-info/RECORD
