Metadata-Version: 2.1
Name: sphinxext-autox
Version: 0.0.2
Summary: Customised version of sphinx.ext.autodoc and sphinx.ext.autosummary
Home-page: UNKNOWN
License: UNKNOWN
Platform: UNKNOWN
Classifier: Programming Language :: Python :: 3
Classifier: Framework :: Sphinx :: Extension
Classifier: License :: OSI Approved :: BSD License
Requires-Python: >=3.5
Requires-Dist: sphinx
